{"userName":"风熏人醉","userId":"ped-yc","homepage":"https://leetcode.cn/u/ped-yc/","logs":[{"date":"2023-03-16","questionIds":[],"reviewQuestionIds":[]},{"date":"2023-03-15","questionIds":["[1615]"],"reviewQuestionIds":[]},{"date":"2023-03-14","questionIds":["[1605]"],"reviewQuestionIds":[]},{"date":"2023-03-13","questionIds":["[2383]"],"reviewQuestionIds":[]},{"date":"2023-03-12","questionIds":["[1617]"],"reviewQuestionIds":[]},{"date":"2023-03-11","questionIds":["[面试题 17.05]"],"reviewQuestionIds":[]},{"date":"2023-03-10","questionIds":["[1590]"],"reviewQuestionIds":[]},{"date":"2023-03-09","questionIds":["[剑指 Offer 47]","[2379]"],"reviewQuestionIds":[]},{"date":"2023-03-08","questionIds":[],"reviewQuestionIds":[]},{"date":"2023-03-07","questionIds":["[1096]"],"reviewQuestionIds":[]},{"date":"2023-03-06","questionIds":["[70]","[1653]"],"reviewQuestionIds":[]},{"date":"2023-03-05","questionIds":["[1599]"],"reviewQuestionIds":[]},{"date":"2023-03-04","questionIds":["[1137]","[509]","[982]"],"reviewQuestionIds":[]},{"date":"2023-03-03","questionIds":["[1487]"],"reviewQuestionIds":[]},{"date":"2023-03-02","questionIds":["[面试题 05.02]"],"reviewQuestionIds":[]},{"date":"2023-03-01","questionIds":["[2373]"],"reviewQuestionIds":[]},{"date":"2023-02-28","questionIds":[],"reviewQuestionIds":[]},{"date":"2023-02-27","questionIds":[],"reviewQuestionIds":[]}],"updatedAt":"2023-03-16T21:13:47+08:00"}