{"userName":"悠悠茶蘼","userId":"dreamjean720","homepage":"https://leetcode-cn.com/u/dreamjean720/","logs":[{"date":"2022-05-08","questionIds":["[456]","[394]","[946]","[1381]","[442]","[6057]","[6056]","[6058]","[6059]","[146]"],"review":[]},{"date":"2022-05-07","questionIds":["[396]","[2258]","[845]","[1004]","[692]","[433]","[127]","[126]"],"review":["[20]"]},{"date":"2022-05-06","questionIds":["[225]","[424]","[438]","[763]","[567]","[933]","[20]","[22]","[520]","[1209]","[1003]","[32]","[414]","[2259]","[剑指 Offer 62]","[274]"],"review":["[225]"]},{"date":"2022-05-05","questionIds":["[713]","[209]","[187]","[76]","[30]","[225]","[41]"]}],"updatedAt":"2022-05-08T21:13:09+08:00"}