{"userName":"杨舟","userId":"sishenhei7","homepage":"https://leetcode.cn/u/sishenhei7/","logs":[{"date":"2022-06-16","questionIds":[],"reviewQuestionIds":[]},{"date":"2022-06-15","questionIds":["[719]"],"reviewQuestionIds":[]},{"date":"2022-06-14","questionIds":["[498]"],"reviewQuestionIds":[]},{"date":"2022-06-13","questionIds":["[1051]"],"reviewQuestionIds":[]},{"date":"2022-06-12","questionIds":["[890]"],"reviewQuestionIds":[]},{"date":"2022-06-11","questionIds":["[926]"],"reviewQuestionIds":[]},{"date":"2022-06-10","questionIds":["[730]"],"reviewQuestionIds":[]},{"date":"2022-06-09","questionIds":["[497]"],"reviewQuestionIds":[]},{"date":"2022-06-08","questionIds":["[1037]"],"reviewQuestionIds":[]},{"date":"2022-06-07","questionIds":["[875]"],"reviewQuestionIds":[]},{"date":"2022-06-06","questionIds":["[732]"],"reviewQuestionIds":[]},{"date":"2022-06-05","questionIds":["[478]"],"reviewQuestionIds":[]},{"date":"2022-06-04","questionIds":["[929]"],"reviewQuestionIds":[]},{"date":"2022-06-03","questionIds":["[829]"],"reviewQuestionIds":[]},{"date":"2022-06-02","questionIds":["[450]"],"reviewQuestionIds":[]},{"date":"2022-06-01","questionIds":["[473]"],"reviewQuestionIds":[]},{"date":"2022-05-31","questionIds":["[剑指 Offer II 114]"],"reviewQuestionIds":[]},{"date":"2022-05-30","questionIds":["[1022]"],"reviewQuestionIds":[]},{"date":"2022-05-29","questionIds":["[468]"],"reviewQuestionIds":[]},{"date":"2022-05-28","questionIds":["[1021]"],"reviewQuestionIds":[]},{"date":"2022-05-27","questionIds":["[面试题 17.11]"],"reviewQuestionIds":[]},{"date":"2022-05-26","questionIds":["[699]"],"reviewQuestionIds":[]},{"date":"2022-05-25","questionIds":["[467]"],"reviewQuestionIds":[]},{"date":"2022-05-24","questionIds":["[965]"],"reviewQuestionIds":[]},{"date":"2022-05-23","questionIds":["[675]"],"reviewQuestionIds":[]},{"date":"2022-05-22","questionIds":["[464]"],"reviewQuestionIds":[]},{"date":"2022-05-21","questionIds":["[961]"],"reviewQuestionIds":[]},{"date":"2022-05-20","questionIds":["[436]"],"reviewQuestionIds":[]},{"date":"2022-05-19","questionIds":["[462]"],"reviewQuestionIds":[]},{"date":"2022-05-18","questionIds":["[668]"],"reviewQuestionIds":[]},{"date":"2022-05-17","questionIds":["[953]"],"reviewQuestionIds":[]},{"date":"2022-05-16","questionIds":["[面试题 04.06]"],"reviewQuestionIds":[]},{"date":"2022-05-15","questionIds":["[812]"],"reviewQuestionIds":[]},{"date":"2022-05-14","questionIds":["[691]"],"reviewQuestionIds":[]},{"date":"2022-05-13","questionIds":["[面试题 01.05]"],"reviewQuestionIds":[]},{"date":"2022-05-12","questionIds":["[944]"],"reviewQuestionIds":[]},{"date":"2022-05-11","questionIds":["[297]","[449]"],"reviewQuestionIds":[]},{"date":"2022-05-10","questionIds":["[1728]"],"reviewQuestionIds":[]},{"date":"2022-05-09","questionIds":["[942]"],"reviewQuestionIds":[]},{"date":"2022-05-08","questionIds":["[442]"],"reviewQuestionIds":[]},{"date":"2022-05-07","questionIds":["[692]","[433]"],"reviewQuestionIds":[]},{"date":"2022-05-06","questionIds":["[933]"],"reviewQuestionIds":[]},{"date":"2022-05-05","questionIds":["[713]"],"reviewQuestionIds":[]}],"updatedAt":"2022-06-16T03:57:36+08:00"}