[
  {
    "userName": "LemonChen",
    "userId": "lemon-chen-t"
  },
  {
    "userName": "你好啊派大星",
    "userId": "ni-hao-a-pai-da-xing"
  },
  {
    "userName": "悠悠茶蘼",
    "userId": "dreamjean720"
  },
  {
    "userName": "杨舟",
    "userId": "sishenhei7"
  },
  {
    "userName": "아이유-意优",
    "userId": "clever-vvilsoneye"
  },
  {
    "userName": "吹过的风",
    "userId": "tinyu"
  },
  {
    "userName": "P丶A",
    "userId": "panxiaoan"
  },
  {
    "userName": "抱枕",
    "userId": "bao-zhen"
  },
  {
    "userName": "Chen",
    "userId": "LilyChenlin"
  },
  {
    "userName": "枫叶",
    "userId": "richard_zhang"
  },
  {
    "userName": "逐晨之梦",
    "userId": "zhu-chen-zhi-meng"
  },
  {
    "userName": "〆、海的思念绵延不绝",
    "userId": "hai-de-si-nian-mian-yan-bu-j-a"
  },
  {
    "userName": "小帅",
    "userId": "wang-xi-fa"
  },
  {
    "userName": "Bear",
    "userId": "beareleven"
  },
  {
    "uerName": "Q.H.Y",
    "userId": "coder-chin"
  },
  {
    "userName": "秃头王路飞",
    "userId": "hardcore-dubinsky1wp"
  },
  {
    "userName": "柯芃丞",
    "userId": "kpc314"
  },
  {
    "userName": "哈哈哈嗯",
    "userId": "younglina"
  },
  {
    "userName": "默海笑",
    "userId": "objective-7iskovx37"
  },
  {
    "userName": "书笙",
    "userId": "shu-sheng-i"
  }
]
